k3process/__init__.py
k3process/_version.py
k3process/ipc.py
k3process/processctrl.py
k3process/scheduler.py
k3process/rpc/__init__.py
k3process/rpc/rpc_client.py
k3process/rpc/rpc_common.py
k3process/rpc/rpc_server.py
k3process-0.4.dist-info/LICENSE
k3process-0.4.dist-info/METADATA
k3process-0.4.dist-info/WHEEL
k3process-0.4.dist-info/entry_points.txt
k3process-0.4.dist-info/top_level.txt
k3process-0.4.dist-info/RECORD
